huefs/huefs.py
huefs-0.0.1a2.dist-info/DESCRIPTION.rst
huefs-0.0.1a2.dist-info/METADATA
huefs-0.0.1a2.dist-info/RECORD
huefs-0.0.1a2.dist-info/WHEEL
huefs-0.0.1a2.dist-info/entry_points.txt
huefs-0.0.1a2.dist-info/metadata.json
huefs-0.0.1a2.dist-info/top_level.txt
