Metadata-Version: 2.0
Name: huefs
Version: 0.0.1a2
Summary: Philips Hue as a FUSE filesystem
Home-page: http://github.com/fusiongyro/huefs
Author: Daniel K Lyons
Author-email: fusion@storytotell.org
License: MIT
Keywords: fuse hue
Platform: UNKNOWN
Classifier: Development Status :: 2 - Pre-Alpha
Classifier: Environment :: No Input/Output (Daemon)
Classifier: Intended Audience :: Developers
Classifier: License :: OSI Approved :: MIT License
Classifier: Operating System :: POSIX :: Linux
Classifier: Natural Language :: English
Classifier: Programming Language :: Python :: 3
Classifier: Topic :: System :: Filesystems
Classifier: Topic :: Home Automation
Requires-Dist: fusepy (<3,>=2.0.4)
Requires-Dist: phue (<2,>=1.0.0)
Requires-Dist: requests (<3,>=2.18)
